README
setup.py
grafana_cassandra/__init__.py
grafana_cassandra/grafana-cassandra.py
grafana_cassandra/server.py
grafana_cassandra.egg-info/PKG-INFO
grafana_cassandra.egg-info/SOURCES.txt
grafana_cassandra.egg-info/dependency_links.txt
grafana_cassandra.egg-info/entry_points.txt
grafana_cassandra.egg-info/requires.txt
grafana_cassandra.egg-info/top_level.txt
grafana_cassandra/config/__init__.py
grafana_cassandra/config/config.py
grafana_cassandra/db_clients/__init__.py
grafana_cassandra/db_clients/cassandra_client.py