Metadata-Version: 1.0
Name: grafana-cassandra
Version: 1.0.0.5
Summary: Json responder to interface between cassandra and grafana
Home-page: UNKNOWN
Author: UNKNOWN
Author-email: UNKNOWN
License: UNKNOWN
Platform: UNKNOWN
